MANIFEST.in
README.org
setup.py
klutshnik/__init__.py
klutshnik/cfg.py
klutshnik/klutshnik.py
klutshnik.egg-info/PKG-INFO
klutshnik.egg-info/SOURCES.txt
klutshnik.egg-info/dependency_links.txt
klutshnik.egg-info/entry_points.txt
klutshnik.egg-info/requires.txt
klutshnik.egg-info/top_level.txt