Metadata-Version: 2.4
Name: klutshnik
Version: 0.3.0
Summary: Klutshnik CLI client
Home-page: https://klutshnik.info/
Author: Stefan Marsiske
Author-email: klutshnik@ctrlc.hu
License: GPLv3
Classifier: Development Status :: 4 - Beta
Classifier: License :: OSI Approved :: GNU General Public License v3 or later (GPLv3+)
Classifier: Topic :: Security :: Cryptography
Classifier: Topic :: Security
Requires-Dist: pysodium
Requires-Dist: pyoprf
Requires-Dist: tomlkit
Dynamic: author
Dynamic: author-email
Dynamic: classifier
Dynamic: description
Dynamic: description-content-type
Dynamic: home-page
Dynamic: license
Dynamic: requires-dist
Dynamic: summary
